Metadata-Version: 2.4
Name: verodat-adri
Version: 7.0.2
Summary: Enterprise data quality layer for AI agents - Validates data quality with Verodat cloud integration. Requires Verodat API key.
Author-email: Thomas Russell <adri@verodat.com>
Maintainer-email: Thomas Russell <adri@verodat.com>
License: Apache License
Project-URL: Homepage, https://github.com/Verodat/verodat-adri
Project-URL: Documentation, https://github.com/Verodat/verodat-adri/blob/main/README.md
Project-URL: Repository, https://github.com/Verodat/verodat-adri
Project-URL: Issues, https://github.com/Verodat/verodat-adri/issues
Project-URL: Changelog, https://github.com/Verodat/verodat-adri/blob/main/CHANGELOG.md
Keywords: data-quality,ai,validation,assessment,reliability,enterprise,verodat
Classifier: Development Status :: 4 - Beta
Classifier: Intended Audience :: Developers
Classifier: Intended Audience :: Science/Research
Classifier: License :: OSI Approved :: Apache Software License
Classifier: Operating System :: OS Independent
Classifier: Programming Language :: Python :: 3
Classifier: Programming Language :: Python :: 3.10
Classifier: Programming Language :: Python :: 3.11
Classifier: Programming Language :: Python :: 3.12
Classifier: Programming Language :: Python :: 3.13
Classifier: Topic :: Scientific/Engineering :: Artificial Intelligence
Classifier: Topic :: Software Development :: Quality Assurance
Classifier: Topic :: Software Development :: Testing
Requires-Python: >=3.10
License-File: LICENSE
License-File: NOTICE
Requires-Dist: pandas>=2.2.2
Requires-Dist: pyyaml>=6.0.2
Requires-Dist: click>=8.1.7
Requires-Dist: pyarrow>=16.1.0
Requires-Dist: tabulate>=0.9.0
Requires-Dist: requests>=2.32.3
Requires-Dist: jsonschema>=4.0.0
Provides-Extra: dev
Requires-Dist: pytest>=8.2.0; extra == "dev"
Requires-Dist: pytest-cov>=5.0.0; extra == "dev"
Requires-Dist: pytest-benchmark>=4.0; extra == "dev"
Requires-Dist: pytest-timeout>=2.1.0; extra == "dev"
Requires-Dist: pytest-mock>=3.12.0; extra == "dev"
Requires-Dist: psutil>=5.9.0; extra == "dev"
Requires-Dist: pre-commit>=3.0.0; extra == "dev"
Requires-Dist: black==25.9.0; extra == "dev"
Requires-Dist: isort>=5.13.2; extra == "dev"
Requires-Dist: flake8>=7.1.1; extra == "dev"
Requires-Dist: mypy>=1.11.2; extra == "dev"
Requires-Dist: pylint>=3.2.6; extra == "dev"
Requires-Dist: bandit[toml]>=1.7.10; extra == "dev"
Requires-Dist: safety>=3.2.8; extra == "dev"
Requires-Dist: pip-audit>=2.7.3; extra == "dev"
Requires-Dist: types-requests>=2.28.0; extra == "dev"
Provides-Extra: test
Requires-Dist: pytest>=8.2.0; extra == "test"
Requires-Dist: pytest-cov>=5.0.0; extra == "test"
Requires-Dist: pytest-benchmark>=4.0; extra == "test"
Requires-Dist: pytest-timeout>=2.1.0; extra == "test"
Requires-Dist: pytest-mock>=3.12.0; extra == "test"
Requires-Dist: psutil>=5.9.0; extra == "test"
Requires-Dist: pyarrow>=14.0.0; extra == "test"
Requires-Dist: tabulate>=0.9.0; extra == "test"
Provides-Extra: security
Requires-Dist: bandit[toml]>=1.7.10; extra == "security"
Requires-Dist: safety>=3.2.8; extra == "security"
Requires-Dist: pip-audit>=2.7.3; extra == "security"
Dynamic: license-file
